pfrl/__init__.py
pfrl/action_value.py
pfrl/agent.py
pfrl/env.py
pfrl/explorer.py
pfrl/policy.py
pfrl/q_function.py
pfrl/replay_buffer.py
pfrl/testing.py
pfrl/agents/__init__.py
pfrl/agents/a2c.py
pfrl/agents/a3c.py
pfrl/agents/acer.py
pfrl/agents/al.py
pfrl/agents/categorical_double_dqn.py
pfrl/agents/categorical_dqn.py
pfrl/agents/ddpg.py
pfrl/agents/double_dqn.py
pfrl/agents/double_pal.py
pfrl/agents/dpp.py
pfrl/agents/dqn.py
pfrl/agents/iqn.py
pfrl/agents/pal.py
pfrl/agents/ppo.py
pfrl/agents/reinforce.py
pfrl/agents/soft_actor_critic.py
pfrl/agents/state_q_function_actor.py
pfrl/agents/td3.py
pfrl/agents/trpo.py
pfrl/collections/__init__.py
pfrl/collections/persistent_collections.py
pfrl/collections/prioritized.py
pfrl/collections/random_access_queue.py
pfrl/distributions/__init__.py
pfrl/distributions/delta.py
pfrl/envs/__init__.py
pfrl/envs/abc.py
pfrl/envs/multiprocess_vector_env.py
pfrl/envs/serial_vector_env.py
pfrl/experiments/__init__.py
pfrl/experiments/evaluator.py
pfrl/experiments/hooks.py
pfrl/experiments/prepare_output_dir.py
pfrl/experiments/train_agent.py
pfrl/experiments/train_agent_async.py
pfrl/experiments/train_agent_batch.py
pfrl/explorers/__init__.py
pfrl/explorers/additive_gaussian.py
pfrl/explorers/additive_ou.py
pfrl/explorers/boltzmann.py
pfrl/explorers/epsilon_greedy.py
pfrl/explorers/greedy.py
pfrl/functions/__init__.py
pfrl/functions/bound_by_tanh.py
pfrl/functions/lower_triangular_matrix.py
pfrl/initializers/__init__.py
pfrl/initializers/chainer_default.py
pfrl/initializers/lecun_normal.py
pfrl/nn/__init__.py
pfrl/nn/atari_cnn.py
pfrl/nn/bound_by_tanh.py
pfrl/nn/branched.py
pfrl/nn/concat_obs_and_action.py
pfrl/nn/empirical_normalization.py
pfrl/nn/lmbda.py
pfrl/nn/mlp.py
pfrl/nn/mlp_bn.py
pfrl/nn/noisy_chain.py
pfrl/nn/noisy_linear.py
pfrl/nn/recurrent.py
pfrl/nn/recurrent_branched.py
pfrl/nn/recurrent_sequential.py
pfrl/optimizers/__init__.py
pfrl/optimizers/rmsprop_eps_inside_sqrt.py
pfrl/policies/__init__.py
pfrl-0.1.0.dist-info/LICENSE
pfrl-0.1.0.dist-info/METADATA
pfrl-0.1.0.dist-info/WHEEL
pfrl-0.1.0.dist-info/top_level.txt
pfrl-0.1.0.dist-info/RECORD
