Metadata-Version: 2.1
Name: pfrl
Version: 0.1.0
Summary: PFRL, a deep reinforcement learning library
Home-page: UNKNOWN
Author: Yasuhiro Fujita
Author-email: fujita@preferred.jp
License: MIT License
Platform: UNKNOWN
Requires-Dist: torch (>=1.3.0)
Requires-Dist: gym (>=0.9.7)
Requires-Dist: numpy (>=1.10.4)
Requires-Dist: pillow
